{"id":"KKGWECA93UTQX","name":"Final Fantasy IX concept art  Final Fantasy Wiki  Fandom","size":86315,"btime":1611840804283,"mtime":1611840804283,"ext":"jpg","tags":[],"folders":["KKGUP4FEUFW80"],"isDeleted":false,"url":"https://finalfantasy.fandom.com/wiki/Final_Fantasy_IX_concept_art?file=Burmecia_Roozbeh_3.jpg","annotation":"","modificationTime":1611840804273,"noThumbnail":true,"width":700,"height":450,"lastModified":1611840804413,"palettes":[{"color":[40,74,105],"ratio":51},{"color":[157,219,244],"ratio":12},{"color":[100,157,209],"ratio":8},{"color":[94,139,176],"ratio":8},{"color":[71,117,162],"ratio":8},{"color":[8,25,45],"ratio":5},{"color":[79,112,141],"ratio":3.63},{"color":[9,27,62],"ratio":0.58}]}