{"id":"KKGWEWEHOZ7G6","name":"Final Fantasy IX concept art  Final Fantasy Wiki  Fandom","size":176215,"btime":1611840830463,"mtime":1611840830687,"ext":"jpg","tags":[],"folders":["KKGUP4FEUFW80"],"isDeleted":false,"url":"https://finalfantasy.fandom.com/wiki/Final_Fantasy_IX_concept_art?file=Evil-Forest2-FFIX.JPG","annotation":"","modificationTime":1611840830345,"noThumbnail":true,"width":860,"height":1000,"lastModified":1611840830808,"palettes":[{"color":[17,29,24],"ratio":58},{"color":[50,76,66],"ratio":16},{"color":[169,193,191],"ratio":11},{"color":[84,118,100],"ratio":10},{"color":[60,87,93],"ratio":1.06},{"color":[128,163,132],"ratio":0.86},{"color":[88,86,72],"ratio":0.36}]}